{
  "cards": [
    {
      "id": 1,
      "title": "App title 1",
      "published": true,
      "user": "Netfront",
      "rating": 4.4,
      "rateCount": 12
    },
    {
      "id": 2,
      "title": "App title 2",
      "published": true,
      "user": "Netfront",
      "rating": 2.7,
      "rateCount": 4
    },
    {
      "id": 3,
      "title": "App title 3",
      "published": false,
      "user": "Netfront",
      "rating": 4.1,
      "rateCount": 7
    },
    {
      "id": 4,
      "title": "App title 4",
      "published": true,
      "user": "Netfront",
      "rating": 4.4,
      "rateCount": 1
    },
    {
      "id": 5,
      "title": "App title 5",
      "published": true,
      "user": "Netfront",
      "rating": 1.7,
      "rateCount": 15
    },
    {
      "id": 6,
      "title": "App title 6",
      "published": true,
      "user": "Netfront",
      "rating": 4,
      "rateCount": null
    },
    {
      "id": 7,
      "title": "App title 7",
      "published": true,
      "user": "Netfront",
      "rating": 4,
      "rateCount": 6
    },
    {
      "id": 8,
      "title": "App title 8",
      "published": false,
      "user": "Netfront",
      "rating": 3.8,
      "rateCount": 7
    },
    {
      "id": 9,
      "title": "App title 9",
      "published": false,
      "user": "Netfront",
      "rating": 2.4,
      "rateCount": 5
    }
  ]
}